{
  "project_info": {
    "project_number": "286227910330",
    "project_id": "gestion-des-colis-36e74",
    "storage_bucket": "gestion-des-colis-36e74.appspot.com"
  },
  "client": [
    {
      "client_info": {
        "mobilesdk_app_id": "1:286227910330:android:55de61d54fe483cf2ffc83",
        "android_client_info": {
          "package_name": "com.awesomeproject"
        }
      },
      "oauth_client": [
        {
          "client_id": "286227910330-uhonp2ntkfvtt0ugk12poj5sk55al43q.apps.googleusercontent.com",
          "client_type": 3
        }
      ],
      "api_key": [
        {
          "current_key": "AIzaSyDm6_BZzfpjyF0sAx_zcTkO1Tb1pht_QdA"
        }
      ],
      "services": {
        "appinvite_service": {
          "other_platform_oauth_client": [
            {
              "client_id": "286227910330-uhonp2ntkfvtt0ugk12poj5sk55al43q.apps.googleusercontent.com",
              "client_type": 3
            }
          ]
        }
      }
    }
  ],
  "configuration_version": "1"
}